debugprint/__init__.py
debugprint/ast2py.py
debugprint/config.py
debugprint/debugprint.py
debugp-0.1.6.dist-info/LICENSE
debugp-0.1.6.dist-info/METADATA
debugp-0.1.6.dist-info/WHEEL
debugp-0.1.6.dist-info/top_level.txt
debugp-0.1.6.dist-info/RECORD
